{
  "phase": "red",
  "behavior_id": "01-model-contract",
  "test_file": "tests/unit/models/test_model_contract.py",
  "tests": {
    "total": 20,
    "collected": 0,
    "passed": 0,
    "failed": 0,
    "errors": 1,
    "skipped": 0
  },
  "expected_failure_reason": "Collection error — missing public API (ProviderKind, ProviderName, RoutingRole, RepairOutcome, ModelAdapter, ModelRequest, ModelResponse, FakeModelAdapter, ModelRouter, StructuredOutputRepair, ModelError, ModelRepair, ModelUsage, get_adapter).",
  "actual_failure_kind": "ImportError / ModuleNotFoundError",
  "verdict": "RED — collection fails because no production module yet exposes the model layer public API."
}
